{"cameraMode":{"drawMode":0,"name":"Shaded","section":"Shading Mode"},"sceneLighting":true,"audioPlay":false,"sceneViewState":{"m_AlwaysRefresh":false,"showFog":true,"showSkybox":true,"showFlares":true,"showImageEffects":true,"showParticleSystems":true,"showVisualEffectGraphs":true,"m_FxEnabled":true},"in2DMode":false,"pivot":{"x":-9.608543395996094,"y":-4.199528217315674,"z":11.247990608215332},"rotation":{"x":0.2164168357849121,"y":-0.7207447290420532,"z":0.2573067247867584,"w":0.6062079668045044},"size":7.187116622924805,"orthographic":false}